gym_xiangqi/__init__.py
gym_xiangqi/board.py
gym_xiangqi/constants.py
gym_xiangqi/piece.py
gym_xiangqi/sound.py
gym_xiangqi/utils.py
gym_xiangqi/xiangqi_game.py
gym_xiangqi/agents/__init__.py
gym_xiangqi/agents/random_agent.py
gym_xiangqi/agents/random_agent_test.py
gym_xiangqi/envs/__init__.py
gym_xiangqi/envs/xiangqi_env.py
gym_xiangqi/examples/__init__.py
gym_xiangqi/examples/agent_v_agent_demo.py
gym_xiangqi/examples/game_mode.py
gym_xiangqi/images/black_pieces/ADV.png
gym_xiangqi/images/black_pieces/ADV_S.png
gym_xiangqi/images/black_pieces/CAN.png
gym_xiangqi/images/black_pieces/CAN_S.png
gym_xiangqi/images/black_pieces/CHR.png
gym_xiangqi/images/black_pieces/CHR_S.png
gym_xiangqi/images/black_pieces/ELE.png
gym_xiangqi/images/black_pieces/ELE_S.png
gym_xiangqi/images/black_pieces/GEN.png
gym_xiangqi/images/black_pieces/GEN_D.png
gym_xiangqi/images/black_pieces/GEN_S.png
gym_xiangqi/images/black_pieces/HRS.png
gym_xiangqi/images/black_pieces/HRS_S.png
gym_xiangqi/images/black_pieces/SOL.png
gym_xiangqi/images/black_pieces/SOL_S.png
gym_xiangqi/images/board/BOARD.png
gym_xiangqi/images/red_pieces/ADV.png
gym_xiangqi/images/red_pieces/ADV_S.png
gym_xiangqi/images/red_pieces/CAN.png
gym_xiangqi/images/red_pieces/CAN_S.png
gym_xiangqi/images/red_pieces/CHR.png
gym_xiangqi/images/red_pieces/CHR_S.png
gym_xiangqi/images/red_pieces/ELE.png
gym_xiangqi/images/red_pieces/ELE_S.png
gym_xiangqi/images/red_pieces/GEN.png
gym_xiangqi/images/red_pieces/GEN_D.png
gym_xiangqi/images/red_pieces/GEN_S.png
gym_xiangqi/images/red_pieces/HRS.png
gym_xiangqi/images/red_pieces/HRS_S.png
gym_xiangqi/images/red_pieces/SOL.png
gym_xiangqi/images/red_pieces/SOL_S.png
gym_xiangqi/sounds/bgm.wav
gym_xiangqi/sounds/bgm_license.pdf
gym_xiangqi/sounds/piece_move.wav
gym_xiangqi-0.5.0.dist-info/LICENSE
gym_xiangqi-0.5.0.dist-info/METADATA
gym_xiangqi-0.5.0.dist-info/WHEEL
gym_xiangqi-0.5.0.dist-info/entry_points.txt
gym_xiangqi-0.5.0.dist-info/top_level.txt
gym_xiangqi-0.5.0.dist-info/RECORD
