Metadata-Version: 2.1
Name: gym-xiangqi
Version: 0.5.0
Summary: Custom OpenAI gym Xiangqi environment
Home-page: https://github.com/tanliyon/gym-xiangqi
Author: Li Yon Tan
Author-email: tan269@purdue.edu
License: UNKNOWN
Platform: UNKNOWN
Classifier: Programming Language :: Python :: 3
Classifier: License :: OSI Approved :: GNU Lesser General Public License v3 (LGPLv3)
Classifier: Operating System :: OS Independent
Requires-Python: >=3.6
